AcademySocket.py
AcademySocket-1.2.0.dist-info/METADATA
AcademySocket-1.2.0.dist-info/WHEEL
AcademySocket-1.2.0.dist-info/top_level.txt
AcademySocket-1.2.0.dist-info/RECORD
