Metadata-Version: 2.1
Name: AcademySocket
Version: 1.2.0
Summary: The Academy Cyber Course
